nucliadb_utils/__init__.py
nucliadb_utils/asyncio_utils.py
nucliadb_utils/authentication.py
nucliadb_utils/const.py
nucliadb_utils/debug.py
nucliadb_utils/exceptions.py
nucliadb_utils/featureflagging.py
nucliadb_utils/grpc.py
nucliadb_utils/helpers.py
nucliadb_utils/nats.py
nucliadb_utils/partition.py
nucliadb_utils/py.typed
nucliadb_utils/run.py
nucliadb_utils/settings.py
nucliadb_utils/signals.py
nucliadb_utils/store.py
nucliadb_utils/transaction.py
nucliadb_utils/utilities.py
nucliadb_utils/audit/__init__.py
nucliadb_utils/audit/audit.py
nucliadb_utils/audit/basic.py
nucliadb_utils/audit/stream.py
nucliadb_utils/cache/__init__.py
nucliadb_utils/cache/exceptions.py
nucliadb_utils/cache/nats.py
nucliadb_utils/cache/pubsub.py
nucliadb_utils/cache/settings.py
nucliadb_utils/encryption/__init__.py
nucliadb_utils/encryption/settings.py
nucliadb_utils/fastapi/__init__.py
nucliadb_utils/fastapi/openapi.py
nucliadb_utils/fastapi/run.py
nucliadb_utils/fastapi/versioning.py
nucliadb_utils/nuclia_usage/__init__.py
nucliadb_utils/nuclia_usage/utils/__init__.py
nucliadb_utils/nuclia_usage/utils/kb_usage_report.py
nucliadb_utils/storages/__init__.py
nucliadb_utils/storages/azure.py
nucliadb_utils/storages/exceptions.py
nucliadb_utils/storages/gcs.py
nucliadb_utils/storages/local.py
nucliadb_utils/storages/nuclia.py
nucliadb_utils/storages/object_store.py
nucliadb_utils/storages/s3.py
nucliadb_utils/storages/settings.py
nucliadb_utils/storages/storage.py
nucliadb_utils/storages/utils.py
nucliadb_utils/tests/__init__.py
nucliadb_utils/tests/asyncbenchmark.py
nucliadb_utils/tests/azure.py
nucliadb_utils/tests/fixtures.py
nucliadb_utils/tests/gcs.py
nucliadb_utils/tests/local.py
nucliadb_utils/tests/nats.py
nucliadb_utils/tests/s3.py
nucliadb_utils-6.11.1.post5854.dist-info/METADATA
nucliadb_utils-6.11.1.post5854.dist-info/WHEEL
nucliadb_utils-6.11.1.post5854.dist-info/top_level.txt
nucliadb_utils-6.11.1.post5854.dist-info/RECORD
