Metadata-Version: 2.4
Name: nucliadb_utils
Version: 6.11.1.post5854
Summary: NucliaDB util library
Author-email: Nuclia <nucliadb@nuclia.com>
License-Expression: AGPL-3.0-or-later
Project-URL: Homepage, https://nuclia.com
Project-URL: Repository, https://github.com/nuclia/nucliadb
Classifier: Development Status :: 4 - Beta
Classifier: Programming Language :: Python
Classifier: Programming Language :: Python :: 3.10
Classifier: Programming Language :: Python :: 3.11
Classifier: Programming Language :: Python :: 3.12
Classifier: Programming Language :: Python :: 3 :: Only
Classifier: Topic :: Software Development :: Libraries :: Python Modules
Requires-Python: <4,>=3.10
Requires-Dist: pydantic>=2.6
Requires-Dist: pydantic-settings>=2.2
Requires-Dist: aiohttp>=3.9.4
Requires-Dist: httpx>=0.27.0
Requires-Dist: prometheus-client>=0.12.0
Requires-Dist: types-requests>=2.27.7
Requires-Dist: mmh3>=3.0.0
Requires-Dist: nats-py[nkeys]>=2.6.0
Requires-Dist: PyNaCl
Requires-Dist: pyjwt>=2.4.0
Requires-Dist: mrflagly>=0.2.14
Requires-Dist: nidx-protos>=6.11.1.post5854
Requires-Dist: nucliadb-protos>=6.11.1.post5854
Requires-Dist: nucliadb-telemetry>=6.11.1.post5854
Provides-Extra: cache
Requires-Dist: redis>=4.3.4; extra == "cache"
Requires-Dist: orjson>=3.6.7; extra == "cache"
Provides-Extra: fastapi
Requires-Dist: fastapi>=0.95.2; extra == "fastapi"
Requires-Dist: starlette>=0.21.0; extra == "fastapi"
Requires-Dist: uvicorn; extra == "fastapi"
Provides-Extra: storages
Requires-Dist: oauth2client>=4.1.3; extra == "storages"
Requires-Dist: aiobotocore>=2.9.0; extra == "storages"
Requires-Dist: google-api-python-client>=2.37.0; extra == "storages"
Requires-Dist: types-aiofiles>=0.8.3; extra == "storages"
Requires-Dist: aiofiles>=0.8.0; extra == "storages"
Requires-Dist: backoff>=1.11.1; extra == "storages"
Requires-Dist: google-auth>=2.4.1; extra == "storages"
Requires-Dist: azure-storage-blob==12.20.0; extra == "storages"
Requires-Dist: azure-identity>=1.16.1; extra == "storages"
